gentrade/__init__.py
gentrade/market_data/__init__.py
gentrade/market_data/core.py
gentrade/market_data/crypto.py
gentrade/market_data/stock_us.py
gentrade/market_data/timeframe.py
gentrade/market_data/util.py
gentrade/strategy/__init__.py
gentrade/strategy/basic.py
gentrade-0.0.21.dist-info/METADATA
gentrade-0.0.21.dist-info/WHEEL
gentrade-0.0.21.dist-info/RECORD
