Metadata-Version: 2.4
Name: gentrade
Version: 0.0.21
Summary: GenAI based Trading Package
Project-URL: Homepage, https://github.com/TrustAgentPlatform/GenTrade
Project-URL: Issues, https://github.com/TrustAgentPlatform/GenTrade/issues
Author-email: Lu Ken <bluewish.ken.lu@live.cn>
Classifier: License :: OSI Approved :: Apache Software License
Classifier: Operating System :: OS Independent
Classifier: Programming Language :: Python :: 3
Requires-Python: >=3.11
Requires-Dist: backtrader
Requires-Dist: ccxt
Requires-Dist: mplfinance
Requires-Dist: ntplib
Requires-Dist: numpy
Requires-Dist: pandas
Requires-Dist: plotly
Requires-Dist: pyautogen
Requires-Dist: pytest
Requires-Dist: wheel
Requires-Dist: yfinance
